MANIFEST.in
README.rst
setup.py
trafaret_validator/__init__.py
trafaret_validator/utils.py
trafaret_validator/validator.py
trafaret_validator.egg-info/PKG-INFO
trafaret_validator.egg-info/SOURCES.txt
trafaret_validator.egg-info/dependency_links.txt
trafaret_validator.egg-info/requires.txt
trafaret_validator.egg-info/top_level.txt